nhl/__init__.py
nhl-0.0.0.dist-info/DESCRIPTION.rst
nhl-0.0.0.dist-info/LICENSE.txt
nhl-0.0.0.dist-info/METADATA
nhl-0.0.0.dist-info/RECORD
nhl-0.0.0.dist-info/WHEEL
nhl-0.0.0.dist-info/metadata.json
nhl-0.0.0.dist-info/top_level.txt
