Metadata-Version: 2.0
Name: nhl
Version: 0.0.0
Summary: Python API for NHL game and player stats
Home-page: https://github.com/mhostetter/nhl
Author: Matt Hostetter
Author-email: matthostetter@gmail.com
License: MIT
Project-URL: Source, https://github.com/mhostetter/nhl
Project-URL: Tracker, https://github.com/mhostetter/nhl/issues
Keywords: nhl hockey sports stats api
Platform: UNKNOWN
Classifier: Development Status :: 1 - Planning
Classifier: Intended Audience :: Developers
Classifier: Intended Audience :: Education
Classifier: Intended Audience :: Science/Research
Classifier: License :: OSI Approved :: MIT License
Classifier: Programming Language :: Python :: 3
Classifier: Programming Language :: Python :: 3.1
Classifier: Programming Language :: Python :: 3.2
Classifier: Programming Language :: Python :: 3.3
Classifier: Programming Language :: Python :: 3.4
Classifier: Programming Language :: Python :: 3.5
Classifier: Programming Language :: Python :: 3.6
Classifier: Programming Language :: Python :: 3 :: Only
Requires-Python: >=3
